flask_babelplus/__init__.py
flask_babelplus/_compat.py
flask_babelplus/constants.py
flask_babelplus/core.py
flask_babelplus/domain.py
flask_babelplus/speaklater.py
flask_babelplus/utils.py
Flask_BabelPlus-2.2.0.dist-info/LICENSE
Flask_BabelPlus-2.2.0.dist-info/METADATA
Flask_BabelPlus-2.2.0.dist-info/WHEEL
Flask_BabelPlus-2.2.0.dist-info/top_level.txt
Flask_BabelPlus-2.2.0.dist-info/RECORD
