Metadata-Version: 1.1
Name: Flask-BabelPlus
Version: 2.2.0
Summary: Adds i18n/l10n support to Flask applications
Home-page: https://github.com/sh4nks/flask-babelplus
Author: Peter Justin
Author-email: peter.justin@outlook.com
License: BSD
Platform: UNKNOWN
Classifier: Development Status :: 5 - Production/Stable
Classifier: Environment :: Web Environment
Classifier: Intended Audience :: Developers
Classifier: License :: OSI Approved :: BSD License
Classifier: Operating System :: OS Independent
Classifier: Programming Language :: Python
Classifier: Programming Language :: Python :: 3
Classifier: Topic :: Internet :: WWW/HTTP :: Dynamic Content
Classifier: Topic :: Software Development :: Libraries :: Python Modules
